libjson2csv/__init__.py
libjson2csv/csv_2_json.py
libjson2csv/json_2_csv.py
libjson2csv/utils.py
libjson2csv-0.1.1.dist-info/DESCRIPTION.rst
libjson2csv-0.1.1.dist-info/METADATA
libjson2csv-0.1.1.dist-info/RECORD
libjson2csv-0.1.1.dist-info/WHEEL
libjson2csv-0.1.1.dist-info/metadata.json
libjson2csv-0.1.1.dist-info/top_level.txt
