Metadata-Version: 1.1
Name: libjson2csv
Version: 0.1.1
Summary: Converts nested json object to csv and csv back to json
Home-page: https://github.com/cnv1989/libjson2csv
Author: Nag Varun Chunduru
Author-email: cnv1989@gmail.com
License: UNKNOWN
Download-URL: https://github.com/cnv1989/libjson2csv/archive/v0.1.1.tar.gz
Keywords: json,csv,converter
Platform: UNKNOWN
